simpleverse/__init__.py
simpleverse/base.py
simpleverse/create_like.py
simpleverse/create_user.py
simpleverse/get_image.py
simpleverse/get_like.py
simpleverse/get_post.py
simpleverse/get_user.py
simpleverse/main.py
simpleverse/py.typed
simpleverse/schemas.py
simpleverse/submit_image.py
simpleverse/submit_post.py
simpleverse-0.9.0.dist-info/LICENSE
simpleverse-0.9.0.dist-info/METADATA
simpleverse-0.9.0.dist-info/WHEEL
simpleverse-0.9.0.dist-info/entry_points.txt
simpleverse-0.9.0.dist-info/top_level.txt
simpleverse-0.9.0.dist-info/RECORD
